{
  "date": "2026-05-20",
  "prev_date": "2026-05-19",
  "trends": {
    "西方奇幻": {
      "new_count": 2,
      "dropped_count": 2,
      "new_books": [
        "身穿西幻，天使降临在我身边",
        "眼盲剑圣当女仆，傲娇千金闹麻了"
      ],
      "dropped_books": [
        {
          "title": "血族大小姐其实是个病娇",
          "intro": "【慢节奏+偏日常+病娇+女强男弱+坏女人+黑暗+微克苏鲁+慢热】 格林失去的从前的所有绝大多数记忆，自身的情感也被淡化。 如今的他接受了血族大小姐莉莉丝的初拥，成为了对方的子嗣。 而自己脑海中竟然出现"
        },
        {
          "title": "血条是倒着的8？那是特喵无限！",
          "intro": "【血量∞+一路乱杀+领主+仆从+魔王+邪恶史莱姆+吞噬升级】 身处蓝星的林夜，穿越到艾特瑞亚，这个游戏世界 但竟穿越到了史莱姆王身上，新手副本的小Boss 【叮！真伤天劫：-999999】林夜被吓了一"
        }
      ],
      "top_risers": [
        {
          "title": "学不会魔法的大乘期修士",
          "change": "+2"
        },
        {
          "title": "转生蒙眼修女的我，真不是深渊种",
          "change": "+2"
        },
        {
          "title": "七元素：异端",
          "change": "+1"
        }
      ],
      "top_fallers": [
        {
          "title": "贵族大小姐下乡三年生七个跑路啦",
          "change": "-2"
        },
        {
          "title": "每日一强化，从横推中世纪开始",
          "change": "-2"
        },
        {
          "title": "魔法少女不该是邪恶干部黄毛",
          "change": "-2"
        }
      ],
      "reads_growth": [
        {
          "title": "金龙领主：在贵族世界的放纵生活",
          "growth": "+1.5万"
        },
        {
          "title": "七元素：异端",
          "growth": "+1.0万"
        },
        {
          "title": "转生蒙眼修女的我，真不是深渊种",
          "growth": "+4000"
        }
      ],
      "summary": "**🔥 题材趋势** 种田领主流+系统面板仍是主流，但\"轻松日常+恋爱\"向作品增速明显；《巫师：让你学知识》以\"无限被动\"创新杀穿万界玩法。\n**📖 读者偏好** 多女主/后宫向读者基础稳固，兽娘、魅魔等亚文化元素接受度高；无女主纯爽文正在打开新市场。\n**🆕 新上榜作品** 《身穿西幻，天使降临在我身边》以\"大汉魅魔\"反差萌突围；《眼盲剑圣当女仆》靠傲娇千金+反差人设吸睛。\n**📉 掉出榜单** 《血族大小姐其实是个病娇》《血条是倒着的8？》因慢热或套路老化掉出。\n**💡 值得关注** \"邪神/魔王\"反转型开局成为新风口；天使、骑士等经典元素的轻喜剧改编值得跟进。"
    },
    "东方仙侠": {
      "new_count": 4,
      "dropped_count": 4,
      "new_books": [
        "二品退休，我在天牢当送饭人",
        "开局帝庭之主：朕全家皆狠角色？",
        "西游：刘备魂穿唐三藏",
        "洪荒我有三十六诸天"
      ],
      "dropped_books": [
        {
          "title": "穿越洪荒，想当宅男的我入劫了",
          "intro": "吴鹏眼睛一睁一闭就来到了海底，好消息是自己穿越了还是洪荒先天大神之一，开局就有阵法保护生命安全，坏消息是自己成了鲲鹏，那个没有伴生灵宝还被赶下了听道蒲团的倒霉孩子。"
        },
        {
          "title": "西游：大师兄住手，那是我兄弟！",
          "intro": "本书又名：李世民：怎么派了个取经的，灵山都来朝贡了！ “大师兄别动手！这妖怪是我拜把子兄弟！” 一句话，让举着金箍棒的孙悟空当场僵住，让一心求经的唐僧彻底麻了。 陵游，万年前穿入西游，没修逆天神功，没"
        },
        {
          "title": "西游之我是牛郎誓死不娶织女",
          "intro": "你问我是谁？吾乃九天司察都检玄衍真君，天庭三大反骨仔之二的师叔，道教护法真君，玄都大法师的师弟，板角青牛的小主人，太上圣人的亲传关门弟子，对，就是专门关门的弟子。 方铭本以为穿越到战国，凭着前世知识，"
        },
        {
          "title": "重生西游，做只稳健猴子",
          "intro": "现代鉴宝专家吴空意外被国宝帮老头开瓢穿越只西游世界，成为刚刚拜师的孙悟空，熟读西游的他知晓西游本是一场阴谋，孙悟空自成为弼马温的那一刻起就成为别人的棋子受人摆布，吴空当即决定，做一只稳健的猴子，原剧情"
        }
      ],
      "top_risers": [
        {
          "title": "听我解释，真不是你们想的那样！",
          "change": "+2"
        },
        {
          "title": "洪荒：开局邂逅云霄，被拐去截教",
          "change": "+2"
        },
        {
          "title": "洪荒：我镇元子，是接引准提大哥",
          "change": "+2"
        }
      ],
      "top_fallers": [
        {
          "title": "穿越成元婴修士，得好好享受才行",
          "change": "-2"
        },
        {
          "title": "我，天庭太子，专治三界恋爱脑",
          "change": "-1"
        },
        {
          "title": "洪荒：拒绝夺舍后，老子杀疯了",
          "change": "-1"
        }
      ],
      "reads_growth": [
        {
          "title": "西游：逆天悟性，师承八戒",
          "growth": "+2.4万"
        },
        {
          "title": "洪荒：苟成大道，被女儿曝光了",
          "growth": "+9000"
        },
        {
          "title": "别人修仙我闲逛，游历三界终长生",
          "growth": "+3000"
        }
      ],
      "summary": "**🔥 题材趋势** 洪荒流+西游流双轨并行，\"苟道修仙\"与\"无敌流\"二分天下；历史人物魂穿（刘备、唐三藏）开辟差异化赛道。\n**📖 读者偏好** 无女主/单女主节奏更受认可，多女主需有强力人设支撑；\"逆天悟性\"\"低调成圣\"等设定满足读者代入感。\n**🆕 新上榜作品** 《二品退休，我在天牢当送饭人》以\"天牢送饭人\"新奇视角突围；《洪荒我有三十六诸天》融合赵公明IP+收集养成玩法。\n**📉 掉出榜单** 《穿越洪荒，想当宅男的我入劫了》《西游之我是牛郎誓死不娶织女》因设定创新不足或节奏问题掉出。\n**💡 值得关注** \"送饭/扫地\"类隐世高人设定正在起量；截教、云霄等封神IP衍生潜力待挖掘。"
    },
    "科幻末世": {
      "new_count": 1,
      "dropped_count": 1,
      "new_books": [
        "末世降临：我却成了无症状感染者"
      ],
      "dropped_books": [
        {
          "title": "末世：穿成大男主的娇弱妹妹",
          "intro": "【末世＋丧尸＋变异动植物】【1v1娇软治愈系妹宝x战力爆表帅哥】 叶熙和穿进一本以末世为背景的大男主小说。 好消息：男主非常疼爱她这个妹妹。 坏消息：她死了。 叶熙和准备好了苟命，却发现……剧情走向怎"
        }
      ],
      "top_risers": [
        {
          "title": "满级女巫在星际封神",
          "change": "+2"
        }
      ],
      "top_fallers": [
        {
          "title": "国运荒野：满级真千金带飞全龙国",
          "change": "-1"
        },
        {
          "title": "你在做饭呢？我在炼制药剂",
          "change": "-1"
        },
        {
          "title": "穿成废土渣渣女，拾荒养娃奔小康",
          "change": "-1"
        }
      ],
      "reads_growth": [
        {
          "title": "末世降临，被六个审判官强制收容",
          "growth": "+1.2万"
        },
        {
          "title": "满级女巫在星际封神",
          "growth": "+3000"
        },
        {
          "title": "魂穿废土，我绑定了三个老公",
          "growth": "+2000"
        }
      ],
      "summary": "**🔥 题材趋势** 末世+系统/穿书仍是核心框架，废土求生、星际种田等融合题材增长明显；男全洁+甜宠成标配设定，女强金手指+爽文模式主导。\n**📖 读者偏好** 在读数断层明显（Top1达25.9万），用户对“极限拉扯”“强制”等高冲突设定买单；双洁甜宠、1VN等情感标签受捧。\n**🆕 新上榜** 《末世降临：我却成了无症状感染者》——以“无异能、无重生”的差异化设定切入，主打女强群像。\n**📉 掉出榜单** 《末世：穿成大男主的娇弱妹妹》（娇软治愈系）掉出，暗示“妹宝”向内容热度降温。\n**💡 值得关注** 《满级女巫在星际封神》排名上升2位，“星际+西幻+军校”融合套路试水有效；Top10门槛约4.8万，中腰部竞争激烈。"
    },
    "都市日常": {
      "new_count": 2,
      "dropped_count": 2,
      "new_books": [
        "压抑大小姐每天都想被亲哭！",
        "睡了姐姐的同学，她竟然是我领导"
      ],
      "dropped_books": [
        {
          "title": "清冷教授攻略中：女儿代练版",
          "intro": "“陆同学，你胆肥啊，敢对老师有想法？” 裴有容双手抱胸，靠在办公室门框上，眼神冷的能冻死人。 “裴教授，您误会了！” “误会？” 她往前踏了一步，高跟鞋叩在地板上，咚的一声，“又送蛋糕又送花的，你说这"
        },
        {
          "title": "不好，捡来的哑巴女是病娇！",
          "intro": "那天陈念在村口赶走一群欺负人的小孩，救了一个浑身是伤的哑巴。 三个月后，她被他养得白净漂亮。 他抱她上床之后，她再也没睡过别处。 他教她吃饭穿衣，教她什么是好人坏人。 她学会了。 她把他教的每一条规矩"
        }
      ],
      "top_risers": [
        {
          "title": "我把你当干妈，你却把当童养夫",
          "change": "+6"
        },
        {
          "title": "黑丝校花纤腰玉腿，恋爱后还超甜",
          "change": "+2"
        },
        {
          "title": "认个首富妈，附赠五位绝色姐姐！",
          "change": "+2"
        }
      ],
      "top_fallers": [
        {
          "title": "狐狸校花不哈气，因为是我捡的",
          "change": "-1"
        },
        {
          "title": "重生后，跟死敌大小姐闪婚了",
          "change": "-1"
        }
      ],
      "reads_growth": [
        {
          "title": "我一个县长，看评论办公怎么了",
          "growth": "+5.8万"
        },
        {
          "title": "他都五次入伍了，你惹他干嘛？",
          "growth": "+2.8万"
        },
        {
          "title": "七岁熊猫烧香，我被老妈上交国家",
          "growth": "+2.3万"
        }
      ],
      "summary": "**🔥 题材趋势** 多女主+修罗场已成标配套路，评分体系新书中增长迅猛；\"后悔流\"（离婚/分手后重生逆转）开始走量；反向养成（年下男主被姐姐们养成）出现差异化突破。**📖 读者偏好** 轻松幽默+甜宠仍是主流，读者对\"评分刚出，会涨\"的标签接受度高，说明对新品容忍度强；多女主修罗场的情感拉扯比单线甜文更能拉动追读。**🆕 新上榜作品** 《压抑大小姐每天都想被亲哭！》（微病娇+姐弟恋）；《睡了姐姐的同学，她竟然是我领导》（暧昧职场+身份反差）。**📉 掉出榜单** 《清冷教授攻略中》《不好，捡来的哑巴女是病娇！》掉出，纯师生禁忌+哑巴病娇等细分套路热度降温。**💡 值得关注** 《三岁送爹入豪门》反向养成+豪门题材融合度好，后续爆发力强；刑侦+女局长题材（《黑丝校花》混入日常榜单）说明跨品类融合正在模糊品类边界。"
    },
    "都市修真": {
      "new_count": 0,
      "dropped_count": 0,
      "new_books": [],
      "dropped_books": [],
      "top_risers": [
        {
          "title": "建立藏书阁：悟空看西游后摆烂了",
          "change": "+3"
        },
        {
          "title": "仙人，你怎么从镜子里出来了！",
          "change": "+2"
        },
        {
          "title": "说好假天师，兄弟你怎么真会？",
          "change": "+1"
        }
      ],
      "top_fallers": [
        {
          "title": "全网在舔紫霞神功，我独修太玄经",
          "change": "-2"
        },
        {
          "title": "重生龙京太子爷，开局修仙就无敌",
          "change": "-1"
        },
        {
          "title": "风流村",
          "change": "-1"
        }
      ],
      "reads_growth": [
        {
          "title": "建立藏书阁：悟空看西游后摆烂了",
          "growth": "+1.3万"
        },
        {
          "title": "风流村",
          "growth": "+1.2万"
        },
        {
          "title": "仙人，你怎么从镜子里出来了！",
          "growth": "+1.1万"
        }
      ],
      "summary": "**🔥 题材趋势** 道士系统流+灵异复苏成头部赛道，鬼故事与爆笑吐槽结合是主流表达；经典IP二次创作（九叔、西游）持续吸量；手游/游戏具现类设定保持稳定输出。**📖 读者偏好** 读者对轻松爽文+快节奏打脸有明显偏好，幽默文风加成显著；跨界两界穿梭设定（《租个天灵根》）因兼顾爽感与新奇感获得加分。**🆕 新上榜作品** 无——榜单稳定，存量竞争激烈。**📉 掉出榜单** 无。**💡 值得关注** 《建立藏书阁》西游记二次创作+系统养成组合新颖，且近期排名上升3位，潜力股；《说\n\n好假天师》以\"假天师\"身份反差切入，笑点密集，与头部《骗子道士》形成赛道双子星格局。"
    },
    "都市高武": {
      "new_count": 1,
      "dropped_count": 1,
      "new_books": [
        "玩个游戏，你们非说我在收容异常"
      ],
      "dropped_books": [
        {
          "title": "说好觉醒空间系，流刃若火咋回事",
          "intro": "评分刚出会涨，每天12点准时更新！ 【全球异能+诸天能力+天才无敌】 灰雾降临，邪神低语。 林缺，西海市公认的学霸，在觉醒日当天，觉醒史无前例的SSS级异能【虚空王座】，引爆全网，被官方奉为百年难遇的"
        }
      ],
      "top_risers": [
        {
          "title": "转职财神：开局充钱到无敌！",
          "change": "+3"
        },
        {
          "title": "全球入侵：我编造了古老薪火组织",
          "change": "+1"
        },
        {
          "title": "挖矿系御兽师的日常生活",
          "change": "+1"
        }
      ],
      "top_fallers": [
        {
          "title": "自首后，国家发现我活了两千年",
          "change": "-1"
        },
        {
          "title": "1枪加1点攻击？我加特林突突突",
          "change": "-1"
        },
        {
          "title": "开局禁区兽皇，捡了个女帝当女儿",
          "change": "-1"
        }
      ],
      "reads_growth": [
        {
          "title": "重生泰坦烛龙，人类你们慌什么？",
          "growth": "+4.3万"
        },
        {
          "title": "开局禁区兽皇，捡了个女帝当女儿",
          "growth": "+4.0万"
        },
        {
          "title": "转职财神：开局充钱到无敌！",
          "growth": "+3.3万"
        }
      ],
      "summary": "**🔥 题材趋势** 跨界IP融合成为新趋势，《X战警》与都市高武结合引发效仿；幕后流、游戏操控、克苏鲁等创新题材加速涌入，差异化竞争加剧。\n**📖 读者偏好** 无敌流、系统流仍是主流基底，搞笑元素和\"无脑爽\"标签提升吸引力；女性向娘化序列证明性别反转题材具备潜力。\n**🆕 新上榜作品** 《玩个游戏，你们非说我在收容异常》以游戏操控+收容异常概念切入，填补了都市高武与SCP风格的融合空白。\n**📉 掉出榜单** 《说好觉醒空间系，流刃若火咋回事》掉出榜单，传统异能觉醒套路竞争力下降。\n**💡 值得关注** 《娘化序列》代表的高概念设定、《全球入侵》的半幕后叙事模式，两者均展现出超越纯战斗升级的内容创新价值。"
    },
    "历史古代": {
      "new_count": 1,
      "dropped_count": 1,
      "new_books": [
        "大秦帝师，天牢教唆扶苏造反"
      ],
      "dropped_books": [
        {
          "title": "重生多尔衮：甩了白月光，夺江山",
          "intro": "《重生多尔衮：甩了白月光，多江山》简介 摄政王多尔衮死了。 他亲手扶上皇位的顺治给了他帝王葬礼，追封“大清成宗义皇帝”。 他以为，这一生值了。 可死后仅三个月，顺治翻脸抄家削爵，将他鞭尸挫骨扬灰。而他"
        }
      ],
      "top_risers": [
        {
          "title": "给你尊荣你不要，来世我去娶郡主",
          "change": "+3"
        },
        {
          "title": "人在大明当差，开局教坊司发老婆",
          "change": "+3"
        },
        {
          "title": "我跟大明太子摊牌了：要么听我的",
          "change": "+2"
        }
      ],
      "top_fallers": [
        {
          "title": "水浒：十龙十象之力，先娶扈三娘",
          "change": "-5"
        },
        {
          "title": "礼佛禁欲等世子，入赘她国你哭啥",
          "change": "-4"
        },
        {
          "title": "我家世代提刀，到我这儿提笔了！",
          "change": "-2"
        }
      ],
      "reads_growth": [
        {
          "title": "大秦：关于我认错祖龙当爹这件事",
          "growth": "+1.8万"
        },
        {
          "title": "给你尊荣你不要，来世我去娶郡主",
          "growth": "+1.4万"
        },
        {
          "title": "红楼之逍遥庶子无所谓",
          "growth": "+1.1万"
        }
      ],
      "summary": "**🔥 题材趋势** 大秦、大唐双雄争霸格局延续，改写历史命运成核心爽点；种田科举、教坊司破案等垂直场景开辟新赛道。\n**📖 读者偏好** 无CP声明强化安全感，科举+日常+权谋三线并行受宠；轻松搞笑风格逐步替代沉重历史叙事。\n**🆕 新上榜作品** 《大秦帝师，天牢教唆扶苏造反》以游戏化视角重解秦末政治，悬念叙事吸睛。\n**📉 掉出榜单** 《重生多尔衮：甩了白月光，夺江山》掉出，清宫多尔衮题材热度有所消退。\n**💡 值得关注** 《农博士手搓稻子》以农学+武侠的反差设定突围，《水浒》融合龙象般若功展现武侠+玄幻混搭潜力，两者代表细分创新方向。"
    },
    "战神赘婿": {
      "new_count": 2,
      "dropped_count": 2,
      "new_books": [
        "穿越女频世界：虐我？一拳打爆！",
        "开局被卖，千亿女总裁拉我领证"
      ],
      "dropped_books": [
        {
          "title": "定下约法三章，冰山老婆先犯规",
          "intro": "曾经执掌全球暗网的陆惊蛰退隐老街，被患有重度恐男症的千亿女董拉去契约结婚。 新婚夜，冰山老婆冷冷甩出协议：“不同房、不触碰、互不干涉，违者净身出户！” 陆惊蛰乐得清闲，主打一个恪守男德，绝不越界。 可"
        },
        {
          "title": "刚下山，就被千亿总裁强拉领证",
          "intro": "“签协议，每月一千万，不同房、不干涉，违约赔十亿！”刚下山的陆渊，转眼就被千亿冰山女总裁夏倾月抓去假婚。陆渊当场狂喜：白拿高薪还不用干活？这班我上定了！ 从此他化身最守男德的赘婿，上班打卡、下班锁门，"
        }
      ],
      "top_risers": [
        {
          "title": "前妻嫌我穷，转身娶了京圈大嫂",
          "change": "+2"
        },
        {
          "title": "让你送外卖：你顺手救了女总裁",
          "change": "+2"
        },
        {
          "title": "都市痞兵：横扫黑白",
          "change": "+1"
        }
      ],
      "top_fallers": [
        {
          "title": "被退婚后，兵王身份藏不住了",
          "change": "-1"
        },
        {
          "title": "冥神殿：冥帅归来！",
          "change": "-1"
        },
        {
          "title": "开局替弟联姻，我见神武圣哭什么",
          "change": "-1"
        }
      ],
      "reads_growth": [
        {
          "title": "都市痞兵：横扫黑白",
          "growth": "+3000"
        },
        {
          "title": "让你送外卖：你顺手救了女总裁",
          "growth": "+283"
        },
        {
          "title": "给神仙姐姐当保镖，她要跟我结婚",
          "growth": "+36"
        }
      ],
      "summary": "**🔥 题材趋势** 身份反差仍是核心引擎，但身份类型从传统兵王向外卖小哥、实习生、契约丈夫等现代职业延伸。\n**📖 读者偏好** 打脸节奏加快，\"净身出户即封王\"模式需求旺盛；多女主与追夫火葬场并行，甜宠元素渗透。\n**🆕 新上榜作品** 《穿越女频世界：虐我？一拳打爆！》以\"一拳打爆\"标题直击爽感，《开局被卖，千亿女总裁拉我领证》将契约婚姻与身份逆袭结合。\n**📉 掉出榜单** 《定下约法三章》《刚下山就被千亿总裁强拉领证》掉出，同质化契约婚姻套路读者审美疲劳。\n**💡 值得关注** 《让你送外卖：你顺手救了女总裁》以\"外卖小哥\"身份切入下沉场景，《霸凌我？大哥带十万大军堵校门》将战神回归与校园霸凌结合，场景创新带动排名上升。"
    },
    "都市种田": {
      "new_count": 1,
      "dropped_count": 1,
      "new_books": [
        "九零年代：冒牌工程师在毛熊捡破"
      ],
      "dropped_books": [
        {
          "title": "狩猎70：猎财猎色猎人生",
          "intro": "（年代+赶山+多女主+爽文） 前世遭污名逃深山15年，归时家族覆灭，一把刀复仇。 重生归来复仇，凭前世狩猎经验上山谋利攒人脉，将家族中兄弟尽数送进体制，让家族崛起登顶。"
        }
      ],
      "top_risers": [
        {
          "title": "收留阿姨母女后，我打猎养活全家",
          "change": "+4"
        },
        {
          "title": "说好小众软件，抖音爆火全球？",
          "change": "+3"
        },
        {
          "title": "财阀家的少公子！",
          "change": "+2"
        }
      ],
      "top_fallers": [],
      "reads_growth": [
        {
          "title": "1960：我的七个孩子有四个妈",
          "growth": "+2.0万"
        },
        {
          "title": "县城：女友出国要我卖房，给脸了",
          "growth": "+1.5万"
        },
        {
          "title": "说好小众软件，抖音爆火全球？",
          "growth": "+1.3万"
        }
      ],
      "summary": "**🔥 题材趋势** 年代重生+空间/系统金手指仍是主流，占榜单近60%；股市投机、科技创业等现代元素与传统种田融合趋势明显，读者对\"搞钱+躺平\"叙事接受度高。\n\n**📖 读者偏好** 都市背景叠加年代感、空间囤货、系统任务三大爽点组合最受欢迎；多女主、轻松无戾气文风持续占优；主角逆袭+打脸渣男的反转剧情点击转化率高。\n\n**🆕 新上榜作品** 《九零年代：冒牌工程师在毛熊捡破》以倒爷+苏联解体背景切入，差异化明显，但口碑待验证。\n\n**📉 掉出榜单** 《狩猎70：猎财猎色猎人生》掉出，年代赶山题材竞争加剧。\n\n**💡 值得关注** 《收留阿姨母女后，我打猎养活全家》排名+4，1979灾荒年+单亲妈妈组合情感张力强；《说好小众软件，抖音爆火全球？》+3，科技穿越+互联网创业赛道新颖。"
    },
    "传统玄幻": {
      "new_count": 1,
      "dropped_count": 1,
      "new_books": [
        "如果外公选择大皇子，满朝皆死！"
      ],
      "dropped_books": [
        {
          "title": "我，女帝赘婿，实则天下无敌！",
          "intro": "【无敌】【扮猪吃虎】【高虐】【杀伐果断】 秦枫，大夏神朝千年难遇的天才，世间最强杀手组织的首领，一身修为超凡入圣，为求真相，他却成了大夏神朝统治下楚国女帝苏曦月的赘婿夫君。 “真是的，女帝陛下怎么嫁给"
        }
      ],
      "top_risers": [
        {
          "title": "征服清冷仙子后，她竟成了我师尊",
          "change": "+4"
        },
        {
          "title": "苟在修仙界：从干女儿上门开始！",
          "change": "+1"
        },
        {
          "title": "天生完美相，我真不是红尘仙！",
          "change": "+1"
        }
      ],
      "top_fallers": [
        {
          "title": "妖路长生：从血瞳玄鸦开始",
          "change": "-4"
        },
        {
          "title": "让你守冷宫，你苟成绝世武神？",
          "change": "-2"
        },
        {
          "title": "转生剑气长城，我是兵家小祖？",
          "change": "-2"
        }
      ],
      "reads_growth": [
        {
          "title": "老六仙二代：底牌全被天幕曝光了",
          "growth": "+1.1万"
        },
        {
          "title": "力量每天增加百分之一我徒手爆星",
          "growth": "+8000"
        },
        {
          "title": "苟在修仙界：从干女儿上门开始！",
          "growth": "+4000"
        }
      ],
      "summary": "**🔥 题材趋势** 修仙流占据主导，老六/苟道写法热度高，系统流仍是标配但向\"系统被主角利用/反杀\"方向演进；无女主/变身题材尝试突破。\n\n**📖 读者偏好** 无敌流、扮猪吃虎节奏紧凑的作品更受青睐；女角色塑造趋向\"反攻略\"，如女帝吸干主角、仙子倒追等反套路设定；杀伐果断+智商在线已成基本门槛。\n\n**🆕 新上榜作品** 《如果外公选择大皇子，满朝皆死！》以预言+权谋切入，玄幻与朝堂结合，题材新颖。\n\n**📉 掉出榜单** 《我，女帝赘婿，实则天下无敌！》掉出，无敌赘婿套路读者新鲜感下降。\n\n**💡 值得关注** 《征服清冷仙子后，她竟成了我师尊》+4，吞噬流+多女主节奏把控出色；《苟在修仙界：从干女儿上门开始！》+1，符道+干女儿上门设定有记忆点。"
    },
    "历史脑洞": {
      "new_count": 2,
      "dropped_count": 2,
      "new_books": [
        "大明：我真不是万寿帝君",
        "唐诡：开局天师传承，雷法镇盛唐"
      ],
      "dropped_books": [
        {
          "title": "谢邀，大唐修仙者，被偷听心声",
          "intro": "一心向往修仙问道的张明渊意外穿越至大唐。 　　脑海中出现一座藏经阁。 　　尝试按照典籍修炼，发现真的能引气入体！ 　　原以为拿到的会是穿越者步步为营，封侯拜将的剧本，没成想会是白日飞升，惟我独仙！ 　"
        },
        {
          "title": "卸磨杀驴？儿臣带兵回京清君侧",
          "intro": "穿越大乾，楚渊成了嫡长子，主动镇守北疆五年，打造出三十万战无不胜的大雪龙骑。 谁料老皇帝晚年昏聩，怕他功高盖主，不仅连下十二道金牌逼他交出兵符，更派三万御林军堵门，甚至送来绝色美人暗中监视，企图“卸磨"
        }
      ],
      "top_risers": [
        {
          "title": "大明老六刚断亲，天幕曝光千古一",
          "change": "+2"
        },
        {
          "title": "水浒：开局在小树林把李逵干死了",
          "change": "+1"
        },
        {
          "title": "朕还没动手，董卓就成忠臣了？",
          "change": "+1"
        }
      ],
      "top_fallers": [
        {
          "title": "假太监，开局签到先天功拿捏皇后",
          "change": "-2"
        },
        {
          "title": "大明：绑定百宝袋，给老朱气笑了",
          "change": "-1"
        },
        {
          "title": "我赵括这一生如履薄冰",
          "change": "-1"
        }
      ],
      "reads_growth": [
        {
          "title": "朕还没动手，董卓就成忠臣了？",
          "growth": "+4.0万"
        },
        {
          "title": "千年家族曝光：世人方知误闯天家",
          "growth": "+3.9万"
        },
        {
          "title": "红楼：杀敌封王，纳妃贾元春",
          "growth": "+1.0万"
        }
      ],
      "summary": "**🔥 题材趋势** 大明题材占绝对主力（近40%），天幕直播/历史揭秘新形式崛起；穿越+系统/金手指仍是核心框架，唐宋明清多朝代并进。\n\n**📖 读者偏好** 轻松搞笑风格受欢迎，读者对\"历史人物被现代知识降维打击\"的爽感买单；幕后流、双主角叙事模式开始分流传统单主角写法；多女主/美人配英雄仍是流量密码。\n\n**🆕 新上榜作品** 《大明：我真不是万寿帝君》以嘉靖+陆炳私生子身份切入，悬疑感强；《唐诡：开局天师传承，雷法镇盛唐》IP联动+国漫风雷法，差异化明显。\n\n**📉 掉出榜单** 《大唐修仙者，被偷听心声》《卸磨杀驴？儿臣带兵回京清君侧》掉出，纯修仙或单纯军事题材热度降温。\n\n**💡 值得关注** 《大明老六刚断亲，天幕曝光千古一》+2，工业大明+躺平皇子设定独特；《朕都妖魔化了，当个暴君很合理吧》女强+魔灾背景稀缺，潜力可期。"
    },
    "悬疑脑洞": {
      "new_count": 2,
      "dropped_count": 2,
      "new_books": [
        "盗墓：祈安卦",
        "盗笔，张家小辈"
      ],
      "dropped_books": [
        {
          "title": "氪金养崽后，哑巴张反向投喂我",
          "intro": "【盗墓同人+脑洞+双向救赎+极度护短+治愈甜宠+爆笑爽文】 林月的破手机里多了个卸不掉的像素游戏。 游戏里有个戴兜帽的小哑巴，天天在雪山挨冻，在古墓放血，孤零零地惨得让人心疼。 母爱泛滥的林月一咬牙，"
        },
        {
          "title": "盗墓：被九门盯上，真的逃不掉啊",
          "intro": "沈墨被一群神经病盯上了。 一个漂亮的穿女装吸引他的注意力， 一个笑面虎天天恐吓他， 一个戴墨镜的总是半夜偷袭，说一些有的没的， 他跑了，但又被抓了回来。 无邪：“还跑吗？” 黑瞎子：“其实读取蛇的费洛"
        }
      ],
      "top_risers": [
        {
          "title": "无限：拒绝和boss贴贴",
          "change": "+4"
        },
        {
          "title": "精神病也要在惊悚游戏谈恋爱",
          "change": "+3"
        },
        {
          "title": "盗笔大舞台，有命你就来！",
          "change": "+2"
        }
      ],
      "top_fallers": [
        {
          "title": "漂亮小可怜在暗黑童话被疯狂觊觎",
          "change": "-1"
        },
        {
          "title": "盗墓神豪系统助我集齐嫩牛五方",
          "change": "-1"
        }
      ],
      "reads_growth": [
        {
          "title": "盗墓：穿成小哥的双胞胎妹妹",
          "growth": "+4000"
        },
        {
          "title": "天幕亮了，放的却是九叔电影",
          "growth": "+1000"
        },
        {
          "title": "盗墓，是玩家不是精分吖",
          "growth": "+1000"
        }
      ],
      "summary": "**🔥 题材趋势**\n\n无限流+副本生存仍是绝对主流，占据榜单70%以上席位。规则怪谈与暗黑童话融合成新风口，「惊悚游戏」标签扎堆出现。盗墓同人保持稳定输出但整体热度下滑。\n\n**📖 读者偏好**\n\n读者偏爱「无CP大女主+爽文节奏」的纯剧情向作品，金手指偏好从系统流转向「规则理解力」「隐藏天赋」等软性设定。轻松搞笑元素接受度高，沉重虐文相对遇冷。\n\n**🆕 新上榜作品**\n\n- 《盗墓：祈安卦》：盗墓同人+悬疑推理，融合卦象设定寻求差异化\n- 《盗笔，张家小辈》：聚焦张家人视角，主打家族群像\n\n**📉 掉出榜单**\n\n- 《氪金养崽后，哑巴张反向投喂我"
    },
    "都市脑洞": {
      "new_count": 1,
      "dropped_count": 1,
      "new_books": [
        "元力引导术，开局满分高考状元"
      ],
      "dropped_books": [
        {
          "title": "满级大佬闯五哈，马甲掉一地",
          "intro": "评分出了，刚出，希望读者大大们给个五星书评，每日稳定更新，不断更，感谢支持！ 【轻松】【搞笑】【日常】【综艺】【系统】【娱乐圈】【单女主】【后浪】 出门买个早餐让白夜撞了大运，因此来到了地球的平行世界"
        }
      ],
      "top_risers": [
        {
          "title": "反派！刚包养的萝莉是主角妹妹？",
          "change": "+4"
        },
        {
          "title": "顶流双手插兜，演唱会只唱开头？",
          "change": "+2"
        },
        {
          "title": "五哈：娱乐第一深情，全网届前任",
          "change": "+1"
        }
      ],
      "top_fallers": [],
      "reads_growth": [
        {
          "title": "反派！刚包养的萝莉是主角妹妹？",
          "growth": "+2.0万"
        },
        {
          "title": "让我开早餐店？我下午才营业",
          "growth": "+1.7万"
        },
        {
          "title": "开局闪婚班主任，岳母是千亿总裁",
          "growth": "+1.6万"
        }
      ],
      "summary": "**🔥 题材趋势**：系统流仍是核心引擎，绑定方式从传统\"任务型\"向\"奇葩场景型\"进化（如开早餐店、钓鱼）；娱乐综艺题材爆发，《五哈》《跑男》等IP改编/综穿文扎堆；科技强国穿越文回温，《芯片之父》《元力引导术》彰显硬核内容需求。\n\n**📖 读者偏好**：\"日常搞笑+系统金手指\"组合最稳，读者对主角\"装逼被拆穿\"桥段乐此不疲；多女主修罗场设定热度高但争议大；悠闲直播/种田流异军突起，《让你去自驾，你成文化顶流了》融合文旅+文化自信获好评。\n\n**🆕 新上榜作品**：《元力引导术，开局满分高考状元》以学霸+黑科技+星际争霸设定空降，题材混搭吸睛。\n\n**📉 掉出榜单**：《满级大佬闯五哈，马甲掉一地》掉出，娱乐综穿赛道竞争白热化。\n\n**💡 值得关注**：《长生四十六亿年》以\"超长待机\"设定制造反差笑点，在读64.7万断层领先；《都市：扮演搬山道人》扮演系统+禁区探险融合度高。"
    },
    "玄幻脑洞": {
      "new_count": 0,
      "dropped_count": 0,
      "new_books": [],
      "dropped_books": [],
      "top_risers": [
        {
          "title": "洪荒：我体内有八亿四千万尊圣人",
          "change": "+3"
        },
        {
          "title": "身为万人迷大师兄的我只想下班",
          "change": "+2"
        },
        {
          "title": "喂丹返修为，开局暴击叛逆女修",
          "change": "+2"
        }
      ],
      "top_fallers": [
        {
          "title": "洞房不让碰，谁惯着你这臭毛病？",
          "change": "-7"
        },
        {
          "title": "飞升后才发现这里是西游",
          "change": "-1"
        },
        {
          "title": "天榜降世我的系统居然被曝光了",
          "change": "-1"
        }
      ],
      "reads_growth": [
        {
          "title": "我都准帝巅峰了，怎么还要收徒",
          "growth": "+3.1万"
        },
        {
          "title": "开局娶丑妻，睡一天涨一年功力",
          "growth": "+2.2万"
        },
        {
          "title": "喂丹返修为，开局暴击叛逆女修",
          "growth": "+1.7万"
        }
      ],
      "summary": "**🔥 题材趋势**：\"退婚流\"\"系统流\"\"苟道流\"三足鼎立，但各流派均融入喜剧元素；洪荒西游同人热度持续，《西游：我爹玉帝》《洪荒：我体内有八亿四千万尊圣人》凭设定创新突围；\"杀伐果断+无女主\"向作品读者忠诚度高，《杀妖涨修为？道爷我成了》空降第5。\n\n**📖 读者偏好**：对\"开局即无敌\"或\"开局被碾压式逆袭\"有强烈爽感需求；师尊/师妹角色塑造趋向\"美强惨+反差萌\"；系统表现方式从纯工具向\"话痨/傲娇\"人格化演变。\n\n**🆕 新上榜作品**：本期无新上榜作品，榜单稳定性强。\n\n**📉 掉出榜单**：无作品掉出，Top 20格局相对固化。\n\n**💡 值得关注**：《卷不动了，让我去外门吧》\"被迫内卷\"社畜共鸣强；《天渊签到二十年》评分9.8，口碑长尾效应显著；《暮年太祖》穿越登基后觉醒设定罕见。"
    },
    "悬疑灵异": {
      "new_count": 2,
      "dropped_count": 2,
      "new_books": [
        "神探狄仁杰：我太子李显多子多福",
        "阴水村"
      ],
      "dropped_books": [
        {
          "title": "人在九叔：摸尸爆出神级天赋",
          "intro": "新作品出炉，欢迎大家前往番茄小说阅读我的作品，希望大家能够喜欢，你们的关注是我写作的动力，我会努力讲好每个故事！"
        },
        {
          "title": "诡异复苏，被我驾驭的厉鬼都死机",
          "intro": "（评分刚出比较低，后面会涨上去。） （神秘复苏设定+爽文+快节奏+原创副本+无女主） 五浊恶世，地狱已空，厉鬼复苏，人间如狱。 我叫萧逸，开局面对诡异的民国老人，驾驭诡嘴 我要吞尽世界一切厉鬼 成为唯"
        }
      ],
      "top_risers": [
        {
          "title": "民间恐怖故事，深夜千万别点开",
          "change": "+4"
        },
        {
          "title": "港九神探：从巡警到重案组大佬",
          "change": "+2"
        },
        {
          "title": "惊天大案纪实",
          "change": "+2"
        }
      ],
      "top_fallers": [
        {
          "title": "茅山天师的现代生活",
          "change": "-3"
        },
        {
          "title": "盗墓：都跟你说了是搬山道人",
          "change": "-3"
        },
        {
          "title": "僵约：应龙血脉，锤爆命运！",
          "change": "-1"
        }
      ],
      "reads_growth": [
        {
          "title": "九叔以为捡个小萌僵，结果是猛僵",
          "growth": "+8000"
        },
        {
          "title": "重生92，我在重案组只想当咸鱼",
          "growth": "+5000"
        },
        {
          "title": "港九神探：从巡警到重案组大佬",
          "growth": "+5000"
        }
      ],
      "summary": "**🔥 题材趋势** \"九叔+僵尸\"类同人大热，前十中占据四席，林正英影视宇宙已成流量密码；法医刑侦赛道崛起，《实习法医》凭系统设定突围；盗墓题材与港风探案持续分流受众。\n\n**📖 读者偏好** 轻松向、成长进化线更受欢迎（#1在读35万远超其他）；系统流+专业技能（法医、风水）组合新颖；无CP/少感情线的\"硬核降妖\"模式接受度高。\n\n**🆕 新上榜作品** 《神探狄仁杰：我太子李显多子多福》融合探案与多子多福系统，脑洞清奇；《阴水村》走乡野怪谈路线，村俗悬疑叙事独特。\n\n**📉 掉出榜单** 《人在九叔：摸尸爆出神级天赋》《诡异复苏，被我驾驭的厉鬼都死机》因评分波动或更新不稳跌出。\n\n**💡 值得关注** #8《民间风水秘术》技术流干货稀缺性强；#19《阴水村》民俗恐怖叙事有差异化潜力。"
    },
    "抗战谍战": {
      "new_count": 2,
      "dropped_count": 2,
      "new_books": [
        "抗战：少帅不好当，我自立门户",
        "军阀：我奉化人，当个总统怎么了"
      ],
      "dropped_books": [
        {
          "title": "亮剑：老李的后勤鬼子看的想报警",
          "intro": "穿越亮剑世界，成了李云龙手下的兵。 好消息：觉醒了技能系统。 坏消息：技能全靠随机。 第一天：【土制炸药·入门】 第二天：【简单外伤包扎·入门】 第三天：【如何辨别可食用野菜·精通】 第……【母猪产后"
        },
        {
          "title": "抗战：亮剑绝命毒师",
          "intro": "抗战】【亮剑】【穿越】【无系统】【毒师】【狠人】【八路军】【反扫荡】【独立团】【热血】【谋略】【护百姓】 吴诚实身上有一个秘密任务，他已经在山西游走了两年，鬼子步步紧逼，他只能回到根据地，依靠组织的能"
        }
      ],
      "top_risers": [
        {
          "title": "亮剑：接替老李，打造最强新一团",
          "change": "+6"
        },
        {
          "title": "天幕，从二战之后开始",
          "change": "+3"
        },
        {
          "title": "抗战：从德械团长到最强军阀！",
          "change": "+2"
        }
      ],
      "top_fallers": [],
      "reads_growth": [
        {
          "title": "抗战：从德械团长到最强军阀！",
          "growth": "+3.8万"
        },
        {
          "title": "军阀：大帅义子，前方到站皇姑屯",
          "growth": "+2.8万"
        },
        {
          "title": "亮剑：接替老李，打造最强新一团",
          "growth": "+1.1万"
        }
      ],
      "summary": "**🔥 题材趋势** 军阀争霸与系统流双线并行，\"少帅/大帅义子\"身份开局成标配；亮剑同人不缺市场，但已从纯穿书转向系统强化变体；民国商贸/发家题材小幅抬头。\n\n**📖 读者偏好** 爽感快节奏刚需，开局即碾压的爽文模式受众广；德械师、抗日先遣队等专业军事设定加分；强调\"杀伐果断\"与热血感。\n\n**🆕 新上榜作品** 《抗战：少帅不好当，我自立门户》《军阀：我奉化人，当个总统怎么了》均为军阀爽文变体，后者走海外建国路线，差异化明显。\n\n**📉 掉出榜单** 《亮剑：老李的后勤鬼子看的想报警》《抗战：亮剑绝命毒师》掉出，亮剑同质化竞争加剧。\n\n**💡 值得关注** #20《军阀：我奉化人，当个总统怎么了》海外复国设定在抗战赛道中稀缺；《民国：开局一百万英镑》商贸+签到系统组合有破圈潜力。"
    },
    "游戏体育": {
      "new_count": 2,
      "dropped_count": 2,
      "new_books": [
        "全民种田：国家霸榜求生游戏",
        "我在KPL当全职野王"
      ],
      "dropped_books": [
        {
          "title": "从无限流回归后，我杀穿末日",
          "intro": "【满级大佬屠杀新手村 + 末日游戏 + 无cp + 爽文】 宁岑寂从无限系统买断“卖身契”归来，存款够挥霍一辈子，只想在原生世界喝茶养猫混吃等死。 下一秒，血月当空，【蚀日乐园】全域通知响彻地球，这个"
        },
        {
          "title": "顿顿鱼肉，你管这叫公路求生？",
          "intro": "【重生+囤货+无CP+经营+系统+公路求生】 第一次穿越到公路求生，林芝满怀热血，最后嘎得默默无闻。 眼睛一闭一睁，竟然回到了被传送前100分钟！ 一百分钟能干什么？ 能在商场来一次大型采购！ 尤其是"
        }
      ],
      "top_risers": [
        {
          "title": "龙岛异兽：逍遥游",
          "change": "+2"
        },
        {
          "title": "海上求生：开局觉醒黑暗料理家",
          "change": "+2"
        },
        {
          "title": "安全屋：榜一她衣橱又又又又满啦",
          "change": "+1"
        }
      ],
      "top_fallers": [
        {
          "title": "全民求生：提前三小时登录",
          "change": "-2"
        },
        {
          "title": "海上求生，魅力点满真的有用吗？",
          "change": "-2"
        },
        {
          "title": "开局绑定父母系统，我想输都难",
          "change": "-1"
        }
      ],
      "reads_growth": [
        {
          "title": "安全屋：榜一她衣橱又又又又满啦",
          "growth": "+3000"
        },
        {
          "title": "网王：外挂是原神系统",
          "growth": "+1000"
        },
        {
          "title": "隐藏玩家：我在求生游戏偷偷升级",
          "growth": "+312"
        }
      ],
      "summary": "**🔥 题材趋势** 全民求生/生存游戏霸榜，垂直场景细分（海洋/公路/沙漠）成新增长点；美食+求生融合开辟差异化赛道，无CP女强占比超七成。\n**📖 读者偏好** 囤货流、欧皇天赋、基建领主元素受欢迎；读者对“开局即满级”“霸榜碾压”爽感需求强烈。\n**🆕 新上榜** 《全民种田：国家霸榜求生游戏》《我在KPL当全职野王》——国家层面叙事+电竞垂直题材试水。\n**📉 掉出榜单** 《从无限流回归后，我杀穿末日》《顿顿鱼肉，你管这叫公路求生？》掉出，公路求生品类后继乏力。\n**💡 值得关注** Top1《网王：外挂是原神系统》在读3.6万，IP联动（网球王子+原神）模式验证可行；海洋求生赛道拥挤但仍有空间。"
    },
    "动漫衍生": {
      "new_count": 1,
      "dropped_count": 1,
      "new_books": [
        "宝可梦：平行女儿曝光，我人麻了"
      ],
      "dropped_books": [
        {
          "title": "聊天群里的光之巨人",
          "intro": "聊天群 + 奥特曼 + 降维打击 + 爆笑吐槽 + 极致暴力 　　这是一个被宇宙战火波及的地球，人类与外星难民共存，安培拉帝国与宙达帝国的阴影在星海中蔓延。 　　作为唯一的“野生光之巨人”，杨渐本想苟"
        }
      ],
      "top_risers": [
        {
          "title": "奥特：开局成为光之债王！",
          "change": "+2"
        },
        {
          "title": "我在战锤抽词条，帝皇站起来了？",
          "change": "+1"
        },
        {
          "title": "原神：被教团抓走，我喊鸽子衔枝",
          "change": "+1"
        }
      ],
      "top_fallers": [
        {
          "title": "火影：抽卡变强？开局金色传说",
          "change": "-1"
        },
        {
          "title": "哥谭蜘蛛侠必须伟光正",
          "change": "-1"
        },
        {
          "title": "人在海贼，开局腕豪模板硬刚卡普",
          "change": "-1"
        }
      ],
      "reads_growth": [
        {
          "title": "我在战锤抽词条，帝皇站起来了？",
          "growth": "+4.4万"
        },
        {
          "title": "咒回：十影术士，受肉重生",
          "growth": "+8000"
        },
        {
          "title": "火影：抽卡变强？开局金色传说",
          "growth": "+6000"
        }
      ],
      "summary": "**🔥 题材趋势** 二次元同人创作持续火热，咒术回战、战锤40K等大IP衍生作品表现亮眼。\"穿越+系统+无敌流\"套路仍是主流，但融合多IP元素的复合型创意正在崛起。火影、海贼王、奥特曼等经典日漫IP改编稳定输出。\n\n**📖 读者偏好** 玩家/粉丝向创作接受度高，喜欢角色融合、系统流、爽文节奏快的作品。幽默吐槽与热血战斗双线并行，《咒回》类作品凭借高人气配角和对抗宿傩的爽感持续吸引流量。\n\n**🆕 新上榜作品** 《宝可梦：平行女儿曝光，我人麻了》凭借天幕+多女主+修罗场设定新进榜单，轻松搞笑风格填补榜单空白。\n\n**📉 掉出榜单** 《聊天群里的光之巨人》掉出榜单，该类聊天群搞笑吐槽向作品热度有所回落。\n\n**💡 值得关注** 《咒回：特级的我去死灭打宿傩了！》以75.8万在读领跑，融合死灭回游+斗傩大陆创意新颖；《我在战锤抽词条，帝皇站起来了？》手电筒开局反差萌吸睛。"
    },
    "男频衍生": {
      "new_count": 3,
      "dropped_count": 3,
      "new_books": [
        "四合院，卫生系将星，给太阳保健",
        "黑袍：从维特鲁姆文员到碎星帝皇",
        "名义：空降汉东，瑞金你急什么？"
      ],
      "dropped_books": [
        {
          "title": "穿越情满四合院，我早到了18年",
          "intro": "评分刚出来有点低，后续会慢慢涨起来的。希望大家喜欢这本书📚！主角有点傻乎乎的，但是绝对不圣母请大家放心阅读！ 主角顾长根被大运百吨王，穿越到情满四合院平行世界，不过早到了18年。穿越到了民国，1947"
        },
        {
          "title": "神雕：魂穿哑仆，开局给黄蓉干活",
          "intro": "【魔改+黄蓉+小龙女+李莫愁+allin】 襄阳城里，所有人都知道郭靖郭大侠——侠之大者，为国为民！ 　　没人在意他府上有个哑仆。 　　扫地、劈柴、喂马、倒泔水，被郭芙踢翻木盆，被武敦儒撞肩膀，被所有"
        },
        {
          "title": "港片：扫黑有速度，警棍有力度！",
          "intro": "一个意外李少君穿越到了港片大世界，成为了一名警察，在这个风起云涌的世界他注定要做出一番大事....."
        }
      ],
      "top_risers": [
        {
          "title": "名义：赵立春女婿，汉东常务副",
          "change": "+4"
        },
        {
          "title": "四合院：被娄家遣散开始崛起！",
          "change": "+1"
        },
        {
          "title": "龙族：我路明非，系统非说是佐助",
          "change": "+1"
        }
      ],
      "top_fallers": [
        {
          "title": "名义：京都直调，开局硬刚沙瑞金",
          "change": "-1"
        }
      ],
      "reads_growth": [
        {
          "title": "士兵突击开局我和许三多发配五班",
          "growth": "+1.5万"
        },
        {
          "title": "穿越黑袍，祖国人成了我兄弟！",
          "growth": "+1.5万"
        },
        {
          "title": "影视世界从成为苏明哲开始",
          "growth": "+8000"
        }
      ],
      "summary": "**🔥 题材趋势** 影视IP二创持续霸榜，《名义》《四合院》《少歌》三大IP形成头部矩阵。官场文、年代穿、综武融合类作品表现稳健，游戏/动漫IP跨界改编开始渗透榜单。\n\n**📖 读者偏好** 雪中悍刀行、影视世界等头部IP粉丝粘性极高，爽文节奏+系统金手指仍是核心竞争力。《士兵突击》类军旅题材凭借差异化脱颖而出，年代文+穿越设定稳定圈粉。\n\n**🆕 新上榜作品** 三本新上榜作品各具特色：《四合院，卫生系将星，给太阳保健》融合卫生系统+亮剑元素创新性强；《黑袍：从维特鲁姆文员到碎星帝皇》超英+进化面板设定吸睛；《名义：空降汉东，瑞金你急什么？》延续官场文热度。\n\n**📉 掉出榜单** 《穿越情满四合院，我早到了18年》《神雕：魂穿哑仆，开局给黄蓉干活》《港片：扫黑有速度，警棍有力度！》掉出榜单，部分题材同质化严重导致竞争力下降。\n\n**💡 值得关注** 《士兵突击开局我和许三多发配五班》以50.4万在读登顶，许三多CP组合+系统任务设定引发热议；《名义》系列持续占据多个席位，官场博弈叙事长盛不衰。"
    },
    "古风世情": {
      "new_count": 1,
      "dropped_count": 1,
      "new_books": [
        "汴京小娘子：靠一手厨艺娇养权臣"
      ],
      "dropped_books": [
        {
          "title": "远古，神赐五百年我延续母系社会",
          "intro": "穿越远古新石器时代，母系文明濒临覆灭，父权部落铁骑踏碎族群安宁，大祭司之女姬炎，在亲人惨死、沦为待宰羔羊的绝境中醒来。 她无系统、无异能，唯有五百年永恒青春的长生天赋，以及远超原始时代的现代顶尖学识与"
        }
      ],
      "top_risers": [
        {
          "title": "无归朝",
          "change": "+2"
        },
        {
          "title": "陛下你跪下，妾身求你点事",
          "change": "+2"
        },
        {
          "title": "穿成李治，我和武后he了",
          "change": "+2"
        }
      ],
      "top_fallers": [
        {
          "title": "冤种世子要我命？几巴掌就服了",
          "change": "-2"
        },
        {
          "title": "快穿：权臣的娇媚女配成了心尖宠",
          "change": "-1"
        },
        {
          "title": "本崽说了算，你有意见？",
          "change": "-1"
        }
      ],
      "reads_growth": [
        {
          "title": "剿匪剿到亲闺女，丞相爹爹崩溃了",
          "growth": "+1.9万"
        },
        {
          "title": "重生：双姝媚骨，撩翻权臣覆江山",
          "growth": "+8000"
        },
        {
          "title": "失忆后，表小姐她移情别恋了",
          "growth": "+8000"
        }
      ],
      "summary": "**🔥 题材趋势**\n\n穿越/重生+复仇仍是主流，共性元素包括替嫁、冲"
    },
    "女频衍生": {
      "new_count": 2,
      "dropped_count": 2,
      "new_books": [
        "黄亦玫重生：这次我选孟宴臣",
        "红楼：黛玉的驯夫之道！"
      ],
      "dropped_books": [
        {
          "title": "斩神：我靠王者系统拯救遗憾",
          "intro": "【斩神+王者+all向+团宠+拆原著CP+私设如山】评分刚出，还会长大滴~ 安禾平平淡淡的生活了十八岁，突然有一天发现自己是穿越的！还是穿越高危的斩神世界！！ 好消息：她有了金手指！还是她最爱的王者农"
        },
        {
          "title": "综影视：佛系路人万事随缘",
          "intro": "【新书刚开分，会涨的！球球小天使们给个机会吧~Orz】【成长型女主，空间是个工具】 熬夜打游戏猝死的安宁，被黑无常踹进了综影视部门，穿梭各影视世界，体验百态人生。且看安宁一个普通人是如何一步步走出自己"
        }
      ],
      "top_risers": [
        {
          "title": "穿成宇宁的前妻后，我赖着不走了",
          "change": "+1"
        },
        {
          "title": "影视：不知道啊！反正人生很曼妙",
          "change": "+1"
        },
        {
          "title": "四合院：我是傻柱大师兄",
          "change": "+1"
        }
      ],
      "top_fallers": [
        {
          "title": "斩神：我靠歌声拯救时间之神",
          "change": "-4"
        },
        {
          "title": "【暮光】燃烧",
          "change": "-3"
        },
        {
          "title": "这个甄嬛传怎么不一样",
          "change": "-2"
        }
      ],
      "reads_growth": [
        {
          "title": "甄嬛传：大小姐驾到，通通闪开",
          "growth": "+1.1万"
        },
        {
          "title": "穿成小燕子：只做乾隆掌中娇宠女",
          "growth": "+1.0万"
        },
        {
          "title": "锦叶良缘",
          "growth": "+5000"
        }
      ],
      "summary": "**🔥 题材趋势**\n综影视/快穿仍是绝对主流，占据榜单80%以上席位。《甄嬛传》系素材出现频率最高，其次为《知否》《如懿传》等古偶IP。系统流+女配逆袭成标配公式，强调“不多不少”的金手指、单元剧独立设定成为新趋势。\n\n**📖 读者偏好**\n以打脸爽文为核心爽点，感情线偏好甜宠/玛丽苏，万人迷元素接受度高。读者对“私设”“魔改”容忍度提升，但强调“正常剧情设定”。\n\n**🆕 新上榜作品**\n- 《黄亦玫重生：这次我选孟宴臣》：玫瑰的故事同人+重生改CP路线，瞄准CP向读者\n- 《红楼：黛玉"
    },
    "玄幻言情": {
      "new_count": 2,
      "dropped_count": 2,
      "new_books": [
        "穿成龙傲天情敌，每天被迫修罗场",
        "女配已就位，薅主角羊毛会上瘾"
      ],
      "dropped_books": [
        {
          "title": "截胡机缘万倍返还，女配偷偷成仙",
          "intro": "（分刚出，会暴涨）[无cp+腹黑+系统+老六+穿书+爽文+横推+偏女强+升级成长] 叶无双穿书成为名剑山庄嫡女，本以为能够躺平摆烂开启咸鱼生活，没曾想才穿越，即将被原书未来的天命女帝百般羞辱，然后要被"
        },
        {
          "title": "穿成废灵根：捡的夫君个个是大佬",
          "intro": "猝死穿越成玄灵大陆废灵根，凤颜歌麻了。 在这个以女为尊，强者为尊的世界，没灵根，还没男人要? 被胞妹同族欺负，还要被生母当做弃子扔掉。 她不想做弃子，她要逆袭变强！ 她有系统，娶夫就能变强，修炼资源那"
        }
      ],
      "top_risers": [
        {
          "title": "这位修士我们人妖殊途啊",
          "change": "+3"
        },
        {
          "title": "资质平平，但顶美",
          "change": "+2"
        },
        {
          "title": "西游：开局骗猴哥当我伴生兽",
          "change": "+2"
        }
      ],
      "top_fallers": [],
      "reads_growth": [
        {
          "title": "这位修士我们人妖殊途啊",
          "growth": "+1.2万"
        },
        {
          "title": "什么，那是阐教大师姐？！",
          "growth": "+9000"
        },
        {
          "title": "怎奈她一身反骨，就爱给众神添堵",
          "growth": "+8000"
        }
      ],
      "summary": "**🔥 题材趋势** 洪荒/封神/西游神话体系持续霸榜，元始天尊、孙悟空等经典IP改编热度不减。系统+穿书仍是主流框架，但\"反派/恶女人设\"和\"沙雕反向操作\"正成为新突破口，女配逆袭、薅羊毛类作品上升势头明显。\n\n**📖 读者偏好** 轻松沙雕文受追捧（如比格女主、 wer哉 wer哉），\"万人迷+男全洁+甜宠\"有稳定受众，洪荒神话背景稳定吸量，反套路设定（女配已就位、穿成龙傲天情敌）有效调动读者猎奇心理。\n\n**🆕 新上榜作品** 《穿成龙傲天情敌，每天被迫修罗场》（台上花）——女扮男装+雄竞修罗场，反派大师兄人设新颖；《女配已就位，薅主角羊毛会上瘾》（一杯甜酒酿）——穿书女配薅主角机缘+氪金系统，爽感直接。\n\n**📉 掉出榜单** 《截胡机缘万倍返还，女配偷偷成仙》《穿成废灵根：捡的夫君个个是大佬》——传统系统流穿书女配文竞争加剧，差异化不足易被迭代。\n\n**💡 值得关注** 榜首《洪荒元始座下白鹤童子》元始天尊背书证明神话体系稳健性；上升作品《这位修士我们人妖殊途啊》+3排名，异类CP（鱼妖×阴湿修士）开辟新赛道；\"无CP向亲情向\"出现破圈迹象。"
    },
    "种田": {
      "new_count": 1,
      "dropped_count": 1,
      "new_books": [
        "养父母恶毒？不伺候！带灵泉分家"
      ],
      "dropped_books": [
        {
          "title": "穿成暴躁肥妇，极品儿子们遭殃了",
          "intro": "【种田】＋【无CP】＋【无金手指】＋【发家致富】＋【家长里短】＋【美食】＋【轻松搞笑】 很幸运，江洛洛穿越了。 很不幸，江洛洛穿越到了极品肥妇身上，二百多斤的体重，奸懒馋滑全占了。 四个儿女也都是极品"
        }
      ],
      "top_risers": [
        {
          "title": "穿越古代，八岁农女带妹闯天下",
          "change": "+1"
        },
        {
          "title": "分家，继母渣爹跪求我回家",
          "change": "+1"
        },
        {
          "title": "开局抄家，我带太孙去逃荒",
          "change": "+1"
        }
      ],
      "top_fallers": [
        {
          "title": "穿成娇软白月光霸王龙它又爱又恨",
          "change": "-1"
        },
        {
          "title": "恶毒前妻再就业，汴京第一妙厨娘",
          "change": "-1"
        },
        {
          "title": "被强嫁傻夫！我靠词条捡满朝权臣",
          "change": "-1"
        }
      ],
      "reads_growth": [
        {
          "title": "穿越古代，八岁农女带妹闯天下",
          "growth": "+4000"
        },
        {
          "title": "刚穿就被卖？我带家人断亲逃荒去",
          "growth": "+3000"
        },
        {
          "title": "悍妻进门：扶起一屋软骨头",
          "growth": "+2000"
        }
      ],
      "summary": "**🔥 题材趋势** 穿越+空间/灵泉/异能金手指成为标配，逃荒、流放等乱世求生题材与种田基建融合；美食+经营路线稳中有升，\"轻松搞笑\"风格读者接受度高；穿书与种田结合出现新变体。\n\n**📖 读者偏好** 女主逆袭+虐渣+分家断亲保持高热，爽感强烈的\"打脸极品亲戚\"情节点击效果显著；美食+经营类（《恶毒前妻再就业》《萌娃通菜市》）有固定受众；古今穿越+萌宝元素（《萌娃通菜市》5.6万在读）开辟新蓝海。\n\n**🆕 新上榜作品** 《养父母恶毒？不伺候！带灵泉分家》（景行斯幽）——穿越假千金复仇+随身空间，经典爽文框架稳定输出。\n\n**📉 掉出榜单** 《穿成暴躁肥妇，极品儿子们遭殃了》——无金手指、无CP的\"纯种田\"在榜单竞争加剧中掉队，读者对金手指依赖度提升。\n\n**💡 值得关注** 《穿越古代，八岁农女带妹闯天下》上升+1，末世异能+空间+无CP组合差异化突出；《被强嫁傻夫！我靠词条捡满朝权臣》词条金手指+傻夫逆袭设定新颖，嫁妆进门、糙汉宠等经典甜梗仍有市场。"
    },
    "年代": {
      "new_count": 1,
      "dropped_count": 1,
      "new_books": [
        "七零拒守活寡，嫁偏执狂军官"
      ],
      "dropped_books": [
        {
          "title": "重生：搬空首富家底去北大荒",
          "intro": "上一世，我是江南顾家的大小姐顾晚。 特殊时期一来，家被抄、人被批斗，爷爷奶奶被逼死，三个哥哥流放惨死，我冻毙在北大荒的雪地里。 睁眼，我竟重生回到了风波前！ 风声已紧，断了联系的二叔一家等着落井下石，"
        }
      ],
      "top_risers": [
        {
          "title": "六零小丧包天天被妖孽首长挂腰上",
          "change": "+3"
        },
        {
          "title": "产双胎，搬家产，我带婆婆去随军",
          "change": "+2"
        },
        {
          "title": "七零：不受宠怎样，偏偏我最争气",
          "change": "+2"
        }
      ],
      "top_fallers": [
        {
          "title": "亲哥重生后，真千金回归了",
          "change": "-1"
        }
      ],
      "reads_growth": [
        {
          "title": "九零：婴语满级，全豪门求我带娃",
          "growth": "+1.5万"
        },
        {
          "title": "村女吴秀丽",
          "growth": "+1.3万"
        },
        {
          "title": "随父入赘后，假娇软成家属院团宠",
          "growth": "+1.3万"
        }
      ],
      "summary": "**🔥 题材趋势**\n\n穿书+金手指+爽文打脸仍是主流，占比超半数；系统任务文明显增多（婴语、红娘系统等猎奇设定）；军婚/军官男主扎堆，随军、婆媳、带娃元素组合频繁出现；重生+虐渣打脸套路稳固，异能/空间+发家致富线热度上升。\n\n**📖 读者偏好**\n\n口味偏向甜宠爽文，偏好「恶毒女配/炮灰逆袭」「虐渣打脸」等高爽感剧情；金手指偏好空间、神笔马良、婴语等创意型设定，单纯武力异能吸引力下降。\n\n**🆕 新上榜作品"
    },
    "现言脑洞": {
      "new_count": 1,
      "dropped_count": 1,
      "new_books": [
        "假千金绝症后，绑定糙汉续命"
      ],
      "dropped_books": [
        {
          "title": "当男频文大反派早死的亲妹觉醒后",
          "intro": "【全息游戏+游戏入侵+金手指大开+无脑爽+重生觉醒+无cp】 【封面是模版封，禁嗑腐】 江梨月死后才知道，自己所在的世界居然是一本男频游戏文。而她，是里面出场不过几次，就因为被霸凌自杀而亡的炮灰。 她"
        }
      ],
      "top_risers": [
        {
          "title": "哥！你再当舔狗我就跟黄毛带球跑",
          "change": "+4"
        },
        {
          "title": "游戏变美系统，我是两百斤女野王",
          "change": "+1"
        },
        {
          "title": "亲妈归来，五个逆子请接驾",
          "change": "+1"
        }
      ],
      "top_fallers": [],
      "reads_growth": [
        {
          "title": "社恐小可怜穿成男主的捞子前女友",
          "growth": "+6.4万"
        },
        {
          "title": "亲妈归来，五个逆子请接驾",
          "growth": "+2.4万"
        },
        {
          "title": "穿成灵异文反派的恶毒女友",
          "growth": "+9000"
        }
      ],
      "summary": "**🔥 题材趋势** 系统文+穿书仍是流量密码，但创新元素更受关注。\"无CP大女主\"标签明显增多，读者对女主专注搞事业的需求上升。萌宝/带崽/团宠文热度持续，变美、带货等现实题材与脑洞融合成新趋势。\n\n**📖 读者偏好** 轻松搞笑+强爽感是核心需求，打脸情节和团宠设定持续受欢迎。系统任务驱动型剧情节奏快、完读率高。男主角\"疯批\"\"阴湿\"属性与女主的拉扯互动依然是流量密码。\n\n**🆕 新上榜作品** 《假千金绝症后，绑定糙汉续命》- 系统+绝症续命+糙汉出租屋元素，\"体型差+极限拉扯\"精准击中特定读者群。\n\n**📉 掉出榜单** 《当男频文大反派早死的亲妹觉醒后》掉出，提示\"全息游戏+觉醒\"类题材竞争加剧。\n\n**💡 值得关注** 《亲妈归来，五个逆子请接驾》《婴语满级》等\"萌娃+系统\"组合表现稳健；带货直播题材《绑定带货系统》代表现实融合新方向。"
    },
    "宫斗宅斗": {
      "new_count": 2,
      "dropped_count": 2,
      "new_books": [
        "假千金被满京权贵疯狂觊觎",
        "丰腴小奶娘，病娇王爷哄生崽"
      ],
      "dropped_books": [
        {
          "title": "穿入1vn文，恶毒女配只想活命",
          "intro": "(刚出分，后续会涨)一次意外，谢安念穿进了一本古早1vn玛丽苏文里，成了里面的恶毒女配。 为了活下去，她开始主动贴近男主，只为傍大腿。 本想借势苟到大结局，却没料到，真正的女主出场后，本该被女主吸引的"
        },
        {
          "title": "媚骨之资！尔等皆为裙下臣",
          "intro": "1vn 架空 甜虐交织 非女强 非爽文 江芷月睁开眼，身上是昨日荒唐后的痕迹，身侧是还没醒的季冥之。 她重生了，重生在了被卫衡送给权臣的第二天。 上一世，她被卫衡辗转送给一个又一个地位显赫的权臣，最后"
        }
      ],
      "top_risers": [
        {
          "title": "挚友之妻",
          "change": "+4"
        },
        {
          "title": "改嫁竹马兄长后，竹马回来了！",
          "change": "+4"
        },
        {
          "title": "重生宠妃不强制爱后，陛下他急了",
          "change": "+4"
        }
      ],
      "top_fallers": [
        {
          "title": "兄长，你敢娶女主我就跟山匪私奔",
          "change": "-6"
        },
        {
          "title": "被迫入宫后，太子他赖上我了",
          "change": "-1"
        },
        {
          "title": "大明：朱元璋老来得女，力大无穷",
          "change": "-1"
        }
      ],
      "reads_growth": [
        {
          "title": "万人觊觎的假公主被拉下高台后",
          "growth": "+2.1万"
        },
        {
          "title": "挚友之妻",
          "growth": "+1.8万"
        },
        {
          "title": "良陈美錦",
          "growth": "+7000"
        }
      ],
      "summary": "**🔥 题材趋势** 甜宠与强取豪夺并行，宫廷权谋元素有回潮迹象。重生复仇、嫡庶之争仍是主流套路。\"雄竞+万人迷\"修罗场模式持续火爆，多男主竞相追逐女主的设定明显增多。\n\n**📖 读者偏好** 甜宠依然是刚需，读者对\"甜中带虐\"\"追妻火葬场\"接受度高。病娇、阴湿男主设定热度不减。宫廷背景下的\"太后+太监\"等非典型CP开始吸引细分受众。\n\n**🆕 新上榜作品** 《假千金被满京权贵疯狂觊觎》（雄竞+阴湿奴隶+强取豪夺）；《丰腴小奶娘，病娇王爷哄生崽》（王爷+奶娘+病娇设定），均为\"娇软美人+强势男主\"组合。\n\n**📉 掉出榜单** 《穿入1vn文，恶毒女配只想活命》《媚骨之资！尔等皆为裙下臣》掉出，低分1VN文市场竞争激烈。\n\n**💡 值得关注** 《皇上表弟说他恕难从命》稳居榜首，年下病弱男主+冤种姐弟设定差异化明显。《改嫁竹马兄长后》排名上升+4，双竹马雄竞赛道值得关注。"
    },
    "古言脑洞": {
      "new_count": 1,
      "dropped_count": 1,
      "new_books": [
        "穿越大清会婴语，百位皇孙抢着宠"
      ],
      "dropped_books": [
        {
          "title": "别惹太子妃，她说谁谁倒霉",
          "intro": "安荣伯府二小姐楚濯春 ，孤煞命格。 三岁被扔去交州。 十五年后被接回京，只为替养女嫁那断腿的世子。 楚濯春牢记师父叮嘱：你乃天定太子妃。 回京第一日，仆妇作妖。楚濯春：嘴脏的人小心掉门牙。 话音落，门"
        }
      ],
      "top_risers": [],
      "top_fallers": [
        {
          "title": "爹别贪了！我哥爬龙床我散财爆红",
          "change": "-1"
        },
        {
          "title": "穿成皇帝的独子",
          "change": "-1"
        }
      ],
      "reads_growth": [
        {
          "title": "沈世子，您真是做男做女都精彩啊",
          "growth": "+9000"
        },
        {
          "title": "天幕曝光后，恶女竟是京城白月光",
          "growth": "+7000"
        },
        {
          "title": "摄政王的白月光亡妻死而复生了",
          "growth": "+5000"
        }
      ],
      "summary": "**🔥 题材趋势** 系统流+金手指仍是核心驱动力，换装、生子、婴语等系统花样翻新。“伪装神女”“穿书维稳”等高概念设定受捧，轻松搞笑元素融入（如书院纨绔逆袭）扩大受众。万人迷+雄竞修罗场模式持续霸榜，萌宝团宠赛道升温。\n\n**📖 读者偏好** 女主智商演技双在线的爽文最吸睛；无CP或纯事业线满足部分读者；系统任务即时反馈契合碎片化阅读；养崽/带娃+古代背景的治愈组合新晋热门。\n\n**🆕 新上榜作品** 《穿越大清会婴语，百位皇孙抢着宠》凭借“婴语系统+清穿+九龙夺嫡”差异化概念突围。\n\n**📉 掉出榜单** 《别惹太子妃，她说谁谁倒霉》被挤出Top20。\n\n**💡 值得关注** 头部《我在乱世靠换装系统装神女》28.7万在读量领先，系统+演技+伪装神女三要素叠加创新高；系统叠加金手指（如婴语+读心）成新突破点；“古代+现代元素穿越融合”赛道持续扩容。"
    },
    "快穿": {
      "new_count": 1,
      "dropped_count": 1,
      "new_books": [
        "快穿：男主不要欺负恶毒女配了！"
      ],
      "dropped_books": [
        {
          "title": "快穿：男配不奉陪",
          "intro": "刚开分，后面会涨【打脸+爽文+男性视角+宠女+系统+技能】 【第一个世界：不当付出一切的深情男配】 情深时男主，受挫时男配？见证男女主踏入婚姻的殿堂，奉献毕生积蓄远走他乡？ 抱歉，他不当这个冤大头，更"
        }
      ],
      "top_risers": [
        {
          "title": "快穿：女主宝宝她实在貌美",
          "change": "+5"
        },
        {
          "title": "病娇又怎么了，可是他独宠啊！",
          "change": "+2"
        },
        {
          "title": "快穿生子：被我渣过的男主他超爱",
          "change": "+2"
        }
      ],
      "top_fallers": [
        {
          "title": "心机女配万人迷，扮乖装茶勾男主",
          "change": "-5"
        },
        {
          "title": "快穿：又又又被大佬叼回窝了",
          "change": "-2"
        },
        {
          "title": "快穿之妾室上位手册",
          "change": "-2"
        }
      ],
      "reads_growth": [
        {
          "title": "被病娇强制爱了怎么办",
          "growth": "+1.0万"
        },
        {
          "title": "恶毒女配她千娇百媚",
          "growth": "+6000"
        },
        {
          "title": "快穿：女主宝宝她实在貌美",
          "growth": "+6000"
        }
      ],
      "summary": "**🔥 题材趋势**\n\n快穿分类持续围绕「女配逆袭」「心机女主」「万人迷」三大核心展开，「绿茶」与「系统"
    },
    "青春甜宠": {
      "new_count": 0,
      "dropped_count": 0,
      "new_books": [],
      "dropped_books": [],
      "top_risers": [
        {
          "title": "穿成恶毒女配后我只想当白富美",
          "change": "+3"
        },
        {
          "title": "回到豪门，我比比格还能闯祸",
          "change": "+1"
        },
        {
          "title": "穿成男主的哭唧唧青梅前女友",
          "change": "+1"
        }
      ],
      "top_fallers": [
        {
          "title": "病弱美人只想搞学习续命",
          "change": "-1"
        },
        {
          "title": "乖乖别躲",
          "change": "-1"
        },
        {
          "title": "哥，你再舔女主我就跟黄毛私奔",
          "change": "-1"
        }
      ],
      "reads_growth": [
        {
          "title": "大小姐雇我替她和太子爷网恋",
          "growth": "+3.4万"
        },
        {
          "title": "回到豪门，我比比格还能闯祸",
          "growth": "+8000"
        },
        {
          "title": "宝宝乖，再亲一口好不好",
          "growth": "+6000"
        }
      ],
      "summary": "《穿成恶毒女配后我只想当白富美》排名上升+3位；《大小姐雇我替她和太子爷网恋》阅读量+3.4万。"
    },
    "星光璀璨": {
      "new_count": 1,
      "dropped_count": 1,
      "new_books": [
        "直播还债，糙汉室友现身后我爆火"
      ],
      "dropped_books": [
        {
          "title": "热搜爆了！影后和她的电竞隐婚夫",
          "intro": "全网热搜轰然爆雷。 影视歌三期出道的人气影后许知瑶，被曝早已隐婚生子。 全网哗然，议论漫天。 所有人都在好奇，究竟是谁，能娶到前途无量的实力派影后。 真相揭开，全网瞬间嘲讽一片。 对方竟是电竞圈的林屿"
        }
      ],
      "top_risers": [
        {
          "title": "团播：神豪系统是我榜一",
          "change": "+5"
        },
        {
          "title": "电子幽灵在主播文里当神豪",
          "change": "+3"
        },
        {
          "title": "AI垄断文娱，我带神曲杀穿全球",
          "change": "+1"
        }
      ],
      "top_fallers": [
        {
          "title": "让你荒野求生，你一根树枝斩野猪",
          "change": "-8"
        },
        {
          "title": "老婆你怎么梦男如此多【万人迷】",
          "change": "-1"
        }
      ],
      "reads_growth": [
        {
          "title": "小宝宝找妈妈，全网抢着要领养",
          "growth": "+1.3万"
        },
        {
          "title": "团播：神豪系统是我榜一",
          "growth": "+2000"
        },
        {
          "title": "穿成炮灰作曲人，我靠神曲杀疯了",
          "growth": "+2000"
        }
      ],
      "summary": "**🔥 题材趋势** 娱乐圈+直播/主播赛道持续火热，万人迷、神豪大哥打赏、PK对战等经典元素迭代出新。穿书/重生+选秀/爱豆成团模式稳定输出，电竞跨界选秀成新亮点。\n\n**📖 读者偏好** 偏好“美强惨”人设与打脸逆袭爽感，对CP类型接受度高（无CP/BG均可）。直播场景要求真实感+弹幕互动，恋综元素可有效拉升热度。\n\n**🆕 新上榜作品** 《直播还债，糙汉室友现身后我爆火》以“软妹VS糙汉”体型差+出租屋室友设定切入，差异化竞争。\n\n**📉 掉出榜单** 《热搜爆了！影后和她的电竞隐婚夫》因现实舆情因素跌出，反映娱乐八卦文对时效敏感。\n\n**💡 值得关注** 《小宝宝找妈妈，全网抢着要领养》直播娃综+萌宝题材契合平台流量，可作为内容方向参考。"
    },
    "女频悬疑": {
      "new_count": 1,
      "dropped_count": 1,
      "new_books": [
        "盗墓：从宝可梦世界走到盗笔世界"
      ],
      "dropped_books": [
        {
          "title": "学霸少女勇闯贵族学校",
          "intro": "【多男主➕玛丽苏➕雄竞➕单箭头】 全员豪门的顶级贵族学校，转来一个一无所有的公费生，全校等着看她笑话。 众人嘲讽她寒门低配、痴心高攀。 殊不知，低调学霸藏锋芒，赛场封神，碾压世家天才，凭实力逆天翻盘！"
        }
      ],
      "top_risers": [
        {
          "title": "刑侦甜妹，在变态修罗场杀疯了",
          "change": "+2"
        },
        {
          "title": "凶案现场，我这个美少女能看见鬼",
          "change": "+1"
        },
        {
          "title": "和张起灵分手后，他要炸了青铜门",
          "change": "+1"
        }
      ],
      "top_fallers": [
        {
          "title": "盗墓：把我睡了的债主又活了",
          "change": "-2"
        },
        {
          "title": "当个社畜，怎么成凶案嫌疑人了？",
          "change": "-1"
        },
        {
          "title": "让让，挡我杀人了",
          "change": "-1"
        }
      ],
      "reads_growth": [
        {
          "title": "盗墓：潘家园有个沈老板",
          "growth": "+1.1万"
        },
        {
          "title": "和张起灵分手后，他要炸了青铜门",
          "growth": "+3000"
        },
        {
          "title": "凶案现场，我这个美少女能看见鬼",
          "growth": "+2000"
        }
      ],
      "summary": "**🔥 题材趋势** 盗墓IP衍生占据半壁江山，张起灵、黑瞎子等角色同人需求旺盛。刑侦+异能（通灵/系统）组合成主流，人物设定趋向“反差萌”（软糯外表+高能破案）。\n\n**📖 读者偏好** 偏爱“女强但不自知”型女主，偏好复杂情感线（狗血拉扯、追妻火葬场）与多男主雄竞修罗场。文笔要求提升，纯恐怖向市场收窄。\n\n**🆕 新上榜作品** 《盗墓：从宝可梦世界走到盗笔世界》以跨世界+宝可梦元素创新，题材新颖度突出。\n\n**📉 掉出榜单** 《学霸少女勇闯贵族学校》因套路趋同、缺乏悬疑核心要素被替代。\n\n**💡 值得关注** 《和张起灵分手后，他要炸了青铜门》盗墓同人+追妻狗血标签组合佳，可作为IP改编方向参考。"
    },
    "职场婚恋": {
      "new_count": 2,
      "dropped_count": 2,
      "new_books": [
        "我被老公骗去缅北",
        "寻子三十年，儿子竟是公司保安"
      ],
      "dropped_books": [
        {
          "title": "查小美不渣，只是没心没肺",
          "intro": "【女主特殊体质不自知、天然渣属性不自知、无贞洁观、脑洞虚构、不喜勿入】 查小美智力有轻微缺陷，不影响生活，就是学习不行。 她迟钝一根筋，忠于自己。 在不影响她的前提下，她很善解人意，孝顺温柔，尊重任何"
        },
        {
          "title": "表白被拒，一觉醒来和男神有了娃",
          "intro": "（评分刚出，后期会涨！）双洁＋男主外科医生×女主颜控，精神状态不详 林雯，18岁的青春美少女，一觉醒来穿到了十年后…… 　　还和拒绝过自己的男神，有了一个五岁的儿子。 　　—— 　　林雯正在跟暗恋的男"
        }
      ],
      "top_risers": [
        {
          "title": "重生后我退了所有单身群",
          "change": "+6"
        },
        {
          "title": "嗜赌村妇，死后只值两万",
          "change": "+5"
        },
        {
          "title": "招惹藏族老板后，女配跑不掉了",
          "change": "+2"
        }
      ],
      "top_fallers": [
        {
          "title": "我当公关的那些日子",
          "change": "-1"
        }
      ],
      "reads_growth": [
        {
          "title": "穿成恶毒女配和落魄男主拼婚养娃",
          "growth": "+4000"
        },
        {
          "title": "重生后我退了所有单身群",
          "growth": "+3000"
        },
        {
          "title": "中奖后我被糙汉军官宠上天",
          "growth": "+2000"
        }
      ],
      "summary": "**🔥 题材趋势** 现实向婚恋题材崛起，“恶婆婆”“离婚逆袭”“闪婚”等冲突型设定受欢迎。职业身份多元化（公关/瑜伽老师/外卖员），缅北诈骗题材首现榜单反映社会热点。\n\n**📖 读者偏好** 偏好“先婚后爱”“追妻火葬场”等拉扯感，对男主“糙汉”“禁欲”人设偏好稳定。闪婚、军婚等快节奏设定可有效降低弃文率。\n\n**🆕 新上榜作品** 《我被老公骗去缅北》以真实诈骗经历+逆袭叙事切入，《寻子三十年，儿子竟是公司保安》以亲情悬念+励志逆袭获关注。\n\n**📉 掉出榜单** 《查小美不渣，只是没心没肺》《表白被拒，一觉醒来和男神有了娃》因题材同质化、评分不稳被替代。\n\n**💡 值得关注** 《中奖后我被糙汉军官宠上天》以“高额奖金+军婚+身高差”多元素叠加稳居榜首，验证复合型设定的高转化率。"
    },
    "豪门总裁": {
      "new_count": 0,
      "dropped_count": 0,
      "new_books": [],
      "dropped_books": [],
      "top_risers": [
        {
          "title": "穿书：开局睡了男主",
          "change": "+2"
        },
        {
          "title": "许我明珠",
          "change": "+1"
        },
        {
          "title": "完蛋，穿成女二她妈，和男主备孕",
          "change": "+1"
        }
      ],
      "top_fallers": [
        {
          "title": "冒名顶替真千金后，嫁入了豪门",
          "change": "-1"
        },
        {
          "title": "宝贝乖，让我亲一下",
          "change": "-1"
        },
        {
          "title": "舔狗不舔了？勿扰！忙着替妈背锅",
          "change": "-1"
        }
      ],
      "reads_growth": [
        {
          "title": "睁眼！太子爷的恶毒女友重生了",
          "growth": "+5.1万"
        },
        {
          "title": "网恋掉马，被重欲金主亲懵了！",
          "growth": "+2.1万"
        },
        {
          "title": "被分手的男友是另一本书男主",
          "growth": "+1.2万"
        }
      ],
      "summary": "**🔥 题材趋势** 重生+豪门+追妻火葬场依旧是流量核心，\"太子爷当狗\"\"上位者低头\"等反转设定持续吸睛。穿书觉醒类作品增多，女主不再是传统傻白甜，而是\"虚荣笨蛋美人\"\"不完美万人迷\"等真实人设更受欢迎。强制爱+熟男熟女组合开始破圈。\n\n**📖 读者偏好** 高在读量作品（《睁眼！太子爷...》90.5万）验证\"重生欺骗+甜宠HE\"复合元素的市场号召力。女主带球跑、恶毒女配反杀、马甲掉马等爽感剧情仍是主流。双洁标签为标配，但\"女非男C\"等非传统设定接受度提升。\n\n**🆕 新上榜作品** 本期无新上榜，榜单整体稳定。\n\n**📉 掉出榜单** 本期无掉出榜单，Top20成员未变。\n\n**💡 值得关注** 《穿书：开局睡了男主》上升2位，穿书+男主非弱精的反套路设定差异化突出。《禁止侵入》\"纯恨对抗路\"标签新颖，双疯批拉扯感强，具备黑马潜质。《湿夜共犯》\"老房子着火\"熟男熟女组合填补市场空白。"
    },
    "民国言情": {
      "new_count": 1,
      "dropped_count": 1,
      "new_books": [
        "穿回四十年代逃荒去上海"
      ],
      "dropped_books": [
        {
          "title": "我在民国续费人生",
          "intro": "【民国日常+金手指签到+轻松搞笑+微群像+青葱岁月+发家致富+背景板男主】 纪少微穿进自己氪过的民国游戏里，月卡只剩六天。不续费，就抹杀。 别人穿游戏是谈恋爱，她穿游戏是搞钱续命。 赛马场押冷门，陆宅"
        }
      ],
      "top_risers": [
        {
          "title": "闪婚，真千金嫁给了军阀大佬",
          "change": "+2"
        },
        {
          "title": "军阀养女：狼崽子的白月光是姐姐",
          "change": "+2"
        },
        {
          "title": "开局1937年：她一心只想求死",
          "change": "+2"
        }
      ],
      "top_fallers": [
        {
          "title": "穿成军统外勤后我杀疯了",
          "change": "-5"
        }
      ],
      "reads_growth": [
        {
          "title": "穿越民国，获得每日签到系统",
          "growth": "+4000"
        },
        {
          "title": "麻将特工",
          "growth": "+1008"
        },
        {
          "title": "人间正道是沧桑：四十年来家国",
          "growth": "+825"
        }
      ],
      "summary": "**🔥 题材趋势** 穿越+系统/签到流（《穿越民国，获得每日签到系统》3.1万在读）带动题材升级，民国谍战与女强元素加速融合。军婚+少帅题材（《捂不热的军婚，她不要了》）回归情感本心，虐恋追妻火葬场仍是情感线主流。\n\n**📖 读者偏好** 女主不再依附男性，\"远渡重洋竖起招牌\"的独立女性叙事获共鸣。系统+直播+家国情怀的跨界组合（《民国直播，带先辈看盛世华夏》）开辟新赛道。失明表妹+强制爱甜宠组合满足多样化阅读需求。\n\n**🆕 新上榜作品** 《穿回四十年代逃荒去上海》新入榜，逃荒+上海买房+黑户逆袭设定，以小人物视角切入乱世，差异化明显。\n\n**📉 掉出榜单** 《我在民国续费人生》掉出榜单，该作金手指签到+日常风格与当前谍战女强趋势偏移。\n\n**💡 值得关注** 《捂不热的军婚，她不要了》稳居榜首，\"东方之美惊艳世界\"的女性独立叙事代表风向。《穿越民国，获得每日签到系统》3.1万在读，系统+谍战+无CP女强组合具备长尾潜力。《掉马后，铁血少帅眼红了》豪门千金×穷酸老师的身份反差设定可关注。"
    }
  }
}